{"cameraMode":{"drawMode":0,"name":"Shaded","section":"Shading Mode"},"sceneLighting":false,"audioPlay":false,"sceneViewState":{"m_AlwaysRefresh":false,"showFog":true,"showSkybox":false,"showFlares":true,"showImageEffects":true,"showParticleSystems":true,"showVisualEffectGraphs":true,"m_FxEnabled":true},"in2DMode":false,"pivot":{"x":-7.919716835021973,"y":0.4898490905761719,"z":19.15752410888672},"rotation":{"x":-0.4684416651725769,"y":-0.0415574349462986,"z":0.02210717462003231,"w":-0.8822752833366394},"size":5.7481889724731449,"orthographic":false}